{"cameraMode":{"drawMode":0,"name":"Shaded","section":"Shading Mode"},"sceneLighting":true,"audioPlay":false,"sceneViewState":{"m_AlwaysRefresh":false,"showFog":true,"showSkybox":true,"showFlares":true,"showImageEffects":true,"showParticleSystems":true,"showVisualEffectGraphs":true,"m_FxEnabled":true},"in2DMode":false,"pivot":{"x":-77.38438415527344,"y":11.868363380432129,"z":63.837852478027347},"rotation":{"x":0.11981267482042313,"y":-0.058223776519298556,"z":0.007060476113110781,"w":0.9910764098167419},"size":5.7228102684021,"orthographic":false}