{"cameraMode":{"drawMode":0,"name":"Shaded","section":"Shading Mode"},"sceneLighting":true,"audioPlay":false,"sceneViewState":{"m_AlwaysRefresh":false,"showFog":true,"showSkybox":true,"showFlares":true,"showImageEffects":true,"showParticleSystems":true,"showVisualEffectGraphs":true,"m_FxEnabled":true},"in2DMode":false,"pivot":{"x":-3.2334790229797365,"y":0.3636770248413086,"z":-1.392449975013733},"rotation":{"x":-0.1129661500453949,"y":0.7227492332458496,"z":-0.12168554961681366,"w":-0.6708803772926331},"size":3.5429768562316896,"orthographic":false}